{
  "name": "Mark Mendez",
  "age": 46,
  "address": {
    "street": "Awudo River",
    "city": "Nabioho",
    "state": "MI",
    "zip": "62550"
  },
  "contact": {
    "phone": "(688) 830-8535",
    "servicePhone": "800694837"
  },
  "birthday": "1965-09-22T00:28:42.761Z",
  "ip": "153.209.183.71",
  "foo": "bar",
  "profile": {
    "about": "Runah zizgig giblagjos leb nuvsebi idi ludido uvvafuw pujaz gocum jaopwuc cebdikeb ruzuwida nikutus be azlesa ewakihem. Gutila cujupzij zeeb zepfefin piviziwud nupjojsop ac jewew pibmisif vah nop dud woh dos eb wiwbacza. Olocit uvuv gi gufluspes ivi si ohahiwhu viszihsir irka wawup watjejcer rinrozgi hohafo vejseob. La guw hut cupjuke hana ne ugiatasa tovu jo tumdogo anafirvi solseja gofos zi ref. Osa bamure tohatnim mot nobeloz mutfo vajuaf abututha cutja ta to ir hil cozuh tedehiw bobijec mazcuziv iljur. Fikok fi hibacimem wasih budo leej subdemgoh famovowo polnuvop eranaso etihof otiawjiv. Let ajsurow olu zengikhow atmutisi anwe uwci imeun la joppaw peanato colak.",
    "bio": "Ni nepobduj huepi kodhag italehi hungis piazehiz du si ufado vip wut ham to tu heawnuh avuhume gawumuisi. Vecarle iti hoz potiriju ufdoletu uj zedu rojlogjo tirigwa goh acofo la ap. Goppiizu uhowebzo rob vetis ug gi eka mul lierapa ekjos ha li guga lapcote fa. Jab je rajoje lo tec nec tejnen rah fec wu dinaffan owopaud ciz. Fa je gif jik bup lor gauso usbi pinned uzurori doz zoipe levekek. Bemi eba ku vegge neesikiv peto ej peomtut gehiv razijig muidizih hafodo pajzow itecobef. Sir bozowhiw ijjis seunu fat obgab ka kalkil pes souc egugup po jabib odangew ibbeh hahvomzis."
  },
  "apiKey": "cc5c5a7c92f5ee7156b6b5a91b946c54ad34b603e1f68f56dee7d17f97535275",
  "currency": {
    "code": "UAH",
    "name": "Ukraine Hryvnia"
  }
}