{
  "name": "Wesley Henry",
  "age": 62,
  "address": {
    "street": "Koef Heights",
    "city": "Necofdo",
    "state": "AR",
    "zip": "33862"
  },
  "contact": {
    "phone": "(958) 613-4778",
    "servicePhone": "800285141"
  },
  "birthday": "1981-11-11T14:28:35.582Z",
  "ip": "178.131.77.246",
  "foo": "bar",
  "profile": {
    "about": "Ag oru hone temzili tuw racsigiw ba hewak henoc vusjadhi pes keve ce winvobmok bawcehun. Umuwecun wod eg lu ni huowovo wi manpiove zeh revtis cin deva kite fuvzow. Vobupilil ledol we dikite socfi oha luwi nugitlu jajimudib puvlomnof wu rebwufjim vojhuclaw. Cozne hug la hop zofej ireco avvulad goltulhi ma wuj soz ruro ez olelkal dili niz ne.",
    "bio": "Pisfon gewmucot cep ri na faeh kic arevu jepbo epcud di jifzi. Gevur luvuwiw jo jifuma rovsaf fiebe upba lumuoc vopha semzihu sujtetuk vo dokvutmah fedi welgag ho jar kot. Den efpa vel etofezo veripi ecsuk silluru ge jugzi evifovis se cagwep nozi. Zaha ceori gir lewocjan mipijni cus jokudu edaso naj bofo ku pigjeut turja oldizdof ruco ke cuz sepro. Givkul fosikcu les ha rehokza cocalfeh ge vijijuj lirdi lepevloz mipet ireru puvlecdu vuk amdool hidnon."
  },
  "apiKey": "914b8dd99a479756bc5974d05f39da5f8949f3a162fdcd279e988e8e8326b0d7",
  "currency": {
    "code": "UZS",
    "name": "Uzbekistan Som"
  }
}