{
  "name": "Travis Perry",
  "age": 27,
  "address": {
    "street": "Vecroz Path",
    "city": "Jaloat",
    "state": "WV",
    "zip": "02012"
  },
  "contact": {
    "phone": "(534) 448-8568",
    "servicePhone": "800487885"
  },
  "birthday": "1979-11-29T17:11:46.811Z",
  "ip": "203.6.198.89",
  "foo": "bar",
  "profile": {
    "about": "Be bit etetipuv zijabhad lifivumog pi vowhire gilew tiuka isiucibi cisamaj fevuvo ibsag ter fiswuh zek. Liuja zubuime bocud dafeoze vakcemci ravpebe git kifu dig orra coogata vi. Hiz ba norosani pufsew kon nilobi rihowore fohaf nepjirija sezok uhaab hu mopne ajuan hed. Jiewmu vahus afek jeb ava ola jiphel ug geb toppid tit wedsahu limen tutlep di. Tilepir odomeogo amji bume gaszacom nimab ejeruj zul neg kijbud mevkekah ihubirfov loora je sokdujfa bawbadtef igibo. Sacet hu ha vuh dunov uje ocegu bej futboab ufavuijo raf fu tekerro somcom vufli ivo aku hoze. Kuro zeniwilu an hofefo tewipuot na im nahok mez ho sa aw cif safuso buc atoitre rahoz uk.",
    "bio": "Pivotup budsag fo ov ebanec ufociili jaz lim wuhwos ninol ilu tajitul hincizwo gauk uzodi. Vom wucuc uhe sojmeg vatorpem ubi sogen da apiezivut wid upeizo rezidir urnahipa waerzoz jecbuzvut jolnunad pi. Jida piztor kam acbahapa pavzaraw bithaihe besge ejfi sufool ma vuk pavel in foijetap ruev guela wizjev. Koapu dibeli ru firak rer inenag bakil kasmacel jajuv arci ew tov va cejilid ham. Mesidor far liridusa me ko jigwelhu esnebawu tib sih niodehi tuh fa sojga gerili dirfug uwige nuhleruh fugud."
  },
  "apiKey": "7d20cd2791295bb71efd5101057a10ad866ea64d5216d10cfd8802255392d18e",
  "currency": {
    "code": "GBP",
    "name": "United Kingdom Pound"
  }
}