{
  "name": "Bruce Hicks",
  "age": 49,
  "address": {
    "street": "Rivpu Street",
    "city": "Irhahvek",
    "state": "OR",
    "zip": "19412"
  },
  "contact": {
    "phone": "(283) 439-9028",
    "servicePhone": "800879799"
  },
  "birthday": "2000-11-02T17:46:26.284Z",
  "ip": "233.138.134.74",
  "foo": "bar",
  "profile": {
    "about": "Jo evo lanipe ihudon imoko urgu mofcip jukwepes tohih tepowo pelkeli ehaivwi ukore niap tagbacit. Vawwaji no daegoowo damut vanoz orumona raktogov ep nam bosulil cawo moc mo niso. Purnaf ehrep cow zesevson otohi haej esudow ozazacak ciwewo saoteba su ivatug rivduldav vewli udowol tif lotoz. Zojgewu lava tuv jaizule hivivpag cevuta rali pofe inafu un opoemaulu timej sit ikuizohu lozke jonuur tajpamon zak. Wiztajgis hebep ca hib iviwanhuk aje lu jarote luh ujerapva opesikic gikzitu ozu is. Jiwjip medespe govti ovo taseshi mucij devebe wu ta duhiv kiganje puci hop uj vileguga us sire.",
    "bio": "Ucine veg uhu ivmafic jiluloj tela kaw banvo tad cegam duj guhejefu dalva vuzracdi ravdehlu pioki. Iv puzmedeb ker soli amza sahen le ke kammal kew uj up powan fehduod ridpad gitaeh ef ev. Rabwup vupum efcethu okomerca keniz noulsu jokni uwkob fitev cah husjocow vor sigizpok osihul. Ujnokdu vicunow jim doreobu ce medi bolefero dirah buzutsu giamiso hekalpu gu benubaba azunahka hi wahji seamuit douji. Fo gohuh luk zahjazit biobi jefot uwjom ujnic neaj hi suavu riparsi ubadaj ze da tifekup. Huvajiwu ugiba vewi tul jizec tinfo vicufu fe gewol anasu rud po re. Arawu ukojolsor uc pujujfir wa zidin fecolig pafwuvit pobse huzohlej woetu elu fis azlenan gavoj ezutadop oje."
  },
  "apiKey": "9897d7ed651a2dae6cfd1979ae86d8631611abdcbb5fee2669fad2dd8966555f",
  "currency": {
    "code": "YER",
    "name": "Yemen Rial"
  }
}