{
  "name": "Virgie Tate",
  "age": 22,
  "address": {
    "street": "Nurlot Point",
    "city": "Hocowli",
    "state": "AZ",
    "zip": "86672"
  },
  "contact": {
    "phone": "(559) 588-1780",
    "servicePhone": "800849854"
  },
  "birthday": "1977-06-15T08:58:36.305Z",
  "ip": "247.68.47.18",
  "foo": "bar",
  "profile": {
    "about": "Fa ole ve nogifug kip junuphiw va cagmos rut ruwnuhi bajek bi puawi. Ziijikik omihesbot juwtap cauhol refvihiz ga gowvu fodizle fuk vidboctaw mah vakijaki avmidna ucikivwu voka. Du suvubwew adiru bidot sugemwe zif ripkew iza duvuger baztelud jano cu bab ohiela aziumaav isa legi tadcav. Iw si bo uj eb hucovo ze puso huij civpeane alku miluli jiz. Gimezu ubwan wic boto ofi onidu emnu nov hieb poiswep bihsepi wewna badu odhej jewvozaw es. Dilve uhluom dip eficaw ris fezrebat ruj erdi difa hopuob kebafraw vuwofe tabo.",
    "bio": "Dehgabzi cibur fezad faben rojdevru lowup ohu riaji wopfo rucegges jezevuke ticdafzo udhocul cermil ovkef onoru mu amu. Cike cirele gado ir mi sanefejon pul ki co lis ganju afibji sigcuki. Pojume foca gocu sibe pergukba gutamu atojohbob jivuzewu getta wejdega kimgo galefituc."
  },
  "apiKey": "75fe4879bad2420fe94395c1fd360c3e6d6469afc3cc3d8a2358a2d23acfb66c",
  "currency": {
    "code": "BHD",
    "name": "Bahrain Dinar"
  }
}